whaler/cli.py
whaler/static/html.tgz
whaler-0.1.2.dist-info/entry_points.txt
whaler-0.1.2.dist-info/LICENSE
whaler-0.1.2.dist-info/WHEEL
whaler-0.1.2.dist-info/METADATA
whaler-0.1.2.dist-info/RECORD
